TCmath/__init__.py
TCmath/cmath.py
TCmath-0.1.0.dist-info/LICENSE
TCmath-0.1.0.dist-info/METADATA
TCmath-0.1.0.dist-info/WHEEL
TCmath-0.1.0.dist-info/top_level.txt
TCmath-0.1.0.dist-info/RECORD
