Metadata-Version: 2.2
Name: TCmath
Version: 0.1.0
Summary: A library for calculating combinations, permutations, and factorials.
Author: Nguyen Truong Chinh
Author-email: chinhcuber@gmail.com
Classifier: Programming Language :: Python :: 3
Classifier: License :: OSI Approved :: MIT License
Classifier: Operating System :: OS Independent
Requires-Python: >=3.6
License-File: LICENSE
Dynamic: author
Dynamic: author-email
Dynamic: classifier
Dynamic: description
Dynamic: description-content-type
Dynamic: requires-python
Dynamic: summary
